MANIFEST.in
README.md
setup.py
version.py
dash_custom_components/1_bootstrap.min.css
dash_custom_components/4_style.default.css
dash_custom_components/5_custom.css
dash_custom_components/InfoBox.py
dash_custom_components/Table.py
dash_custom_components/__init__.py
dash_custom_components/_imports_.py
dash_custom_components/dash_custom_components.dev.js
dash_custom_components/dash_custom_components.min.js
dash_custom_components/metadata.json
dash_custom_components/package.json
dash_custom_components/version.py
dash_custom_components.egg-info/PKG-INFO
dash_custom_components.egg-info/SOURCES.txt
dash_custom_components.egg-info/dependency_links.txt
dash_custom_components.egg-info/top_level.txt