Metadata-Version: 1.0
Name: dash-custom-components
Version: 4.0.1
Summary: Some description
Home-page: UNKNOWN
Author: Martin Rode
Author-email: UNKNOWN
License: BSD
Platform: UNKNOWN
